django_casper-0.0.4.dist-info/metadata.json
django_casper-0.0.4.dist-info/DESCRIPTION.rst
django_casper-0.0.4.dist-info/METADATA
django_casper-0.0.4.dist-info/WHEEL
django_casper-0.0.4.dist-info/RECORD
django_casper-0.0.4.dist-info/top_level.txt
casper/views.py
casper/models.py
casper/__init__.py
casper/tests.py
